WeiXueyuanCYuyanJiaochengFix1/README.md
WeiXueyuanCYuyanJiaochengFix1/__init__.py
WeiXueyuanCYuyanJiaochengFix1/__main__.py
WeiXueyuanCYuyanJiaochengFix1/file.epub
WeiXueyuanCYuyanJiaochengFix1/index.html
WeiXueyuanCYuyanJiaochengFix1/css/__init__.py
WeiXueyuanCYuyanJiaochengFix1/css/annotations.css
WeiXueyuanCYuyanJiaochengFix1/css/main.css
WeiXueyuanCYuyanJiaochengFix1/css/normalize.css
WeiXueyuanCYuyanJiaochengFix1/css/popup.css
WeiXueyuanCYuyanJiaochengFix1/font/__init__.py
WeiXueyuanCYuyanJiaochengFix1/font/fontello.eot
WeiXueyuanCYuyanJiaochengFix1/font/fontello.svg
WeiXueyuanCYuyanJiaochengFix1/font/fontello.ttf
WeiXueyuanCYuyanJiaochengFix1/font/fontello.woff
WeiXueyuanCYuyanJiaochengFix1/img/__init__.py
WeiXueyuanCYuyanJiaochengFix1/img/annotator-glyph-sprite.png
WeiXueyuanCYuyanJiaochengFix1/img/annotator-icon-sprite.png
WeiXueyuanCYuyanJiaochengFix1/img/apple-touch-icon.png
WeiXueyuanCYuyanJiaochengFix1/img/cancelfullscreen.png
WeiXueyuanCYuyanJiaochengFix1/img/close.png
WeiXueyuanCYuyanJiaochengFix1/img/fullscreen.png
WeiXueyuanCYuyanJiaochengFix1/img/loader.gif
WeiXueyuanCYuyanJiaochengFix1/img/menu-icon.png
WeiXueyuanCYuyanJiaochengFix1/img/save.png
WeiXueyuanCYuyanJiaochengFix1/img/saved.png
WeiXueyuanCYuyanJiaochengFix1/img/settings-s.png
WeiXueyuanCYuyanJiaochengFix1/img/settings.png
WeiXueyuanCYuyanJiaochengFix1/img/star.png
WeiXueyuanCYuyanJiaochengFix1/js/__init__.py
WeiXueyuanCYuyanJiaochengFix1/js/epub.js
WeiXueyuanCYuyanJiaochengFix1/js/epub.min.js
WeiXueyuanCYuyanJiaochengFix1/js/epub.min.map
WeiXueyuanCYuyanJiaochengFix1/js/hooks.min.js
WeiXueyuanCYuyanJiaochengFix1/js/hooks.min.map
WeiXueyuanCYuyanJiaochengFix1/js/reader.js
WeiXueyuanCYuyanJiaochengFix1/js/reader.js.map
WeiXueyuanCYuyanJiaochengFix1/js/reader.min.js
WeiXueyuanCYuyanJiaochengFix1/js/reader.min.map
WeiXueyuanCYuyanJiaochengFix1/js/hooks/__init__.py
WeiXueyuanCYuyanJiaochengFix1/js/hooks/extensions/__init__.py
WeiXueyuanCYuyanJiaochengFix1/js/hooks/extensions/highlight.js
wei_xueyuan_c_yuyan_jiaocheng_fix1-2025.3.25.0.dist-info/METADATA
wei_xueyuan_c_yuyan_jiaocheng_fix1-2025.3.25.0.dist-info/WHEEL
wei_xueyuan_c_yuyan_jiaocheng_fix1-2025.3.25.0.dist-info/entry_points.txt
wei_xueyuan_c_yuyan_jiaocheng_fix1-2025.3.25.0.dist-info/top_level.txt
wei_xueyuan_c_yuyan_jiaocheng_fix1-2025.3.25.0.dist-info/RECORD
